setup.py
basics/__init__.py
basics/basics.py
coolBasics.egg-info/PKG-INFO
coolBasics.egg-info/SOURCES.txt
coolBasics.egg-info/dependency_links.txt
coolBasics.egg-info/top_level.txt