Metadata-Version: 1.1
Name: coolBasics
Version: 0.1
Summary: A Python module for having fun!
Home-page: UNKNOWN
Author: Arca Ege Cengiz
Author-email: arcaegecengiz@gmail.com
License: UNKNOWN
Keywords: fun,python,basics,learning,motivation
Platform: UNKNOWN
Classifier: Development Status :: 3 - Alpha
Classifier: Intended Audience :: Education
Classifier: Programming Language :: Python :: 3
